pastax/__init__.py
pastax/_version.py
pastax/dynamics/__init__.py
pastax/dynamics/_linear_uv.py
pastax/dynamics/_smagorinsky_diffusion.py
pastax/evaluation/__init__.py
pastax/evaluation/_evaluation.py
pastax/evaluation/_evaluator.py
pastax/evaluation/_metric.py
pastax/gridded/__init__.py
pastax/gridded/_coordinate.py
pastax/gridded/_field.py
pastax/gridded/_gridded.py
pastax/gridded/_operators.py
pastax/simulator/__init__.py
pastax/simulator/_base_simulator.py
pastax/simulator/_diffrax_simulator.py
pastax/trajectory/__init__.py
pastax/trajectory/_set.py
pastax/trajectory/_state.py
pastax/trajectory/_states.py
pastax/trajectory/_timeseries.py
pastax/trajectory/_timeseries_ensemble.py
pastax/trajectory/_trajectory.py
pastax/trajectory/_trajectory_ensemble.py
pastax/trajectory/_unitful.py
pastax/utils/__init__.py
pastax/utils/_geo.py
pastax/utils/_unit.py
pastax-0.0.6.dist-info/licenses/LICENSE
pastax-0.0.6.dist-info/METADATA
pastax-0.0.6.dist-info/WHEEL
pastax-0.0.6.dist-info/top_level.txt
pastax-0.0.6.dist-info/RECORD
